clientutils/__init__.py
clientutils/clipboard.py
clientutils/cmd.py
clientutils/fileaccess.py
clientutils/fileinfo.py
clientutils/fileresource.py
clientutils/pathmapping.py
clientutils/version.py
clientutils/webserver.py
clientutils_examples/__init__.py
clientutils_examples/icons/.png
clientutils_examples/icons/7z32x32.png
clientutils_examples/icons/aac32x32.png
clientutils_examples/icons/ai32x32.png
clientutils_examples/icons/aif32x32.png
clientutils_examples/icons/aiff32x32.png
clientutils_examples/icons/avi32x32.png
clientutils_examples/icons/awk.xcf
clientutils_examples/icons/awk32x32.png
clientutils_examples/icons/bat32x32.png
clientutils_examples/icons/bin32x32.png
clientutils_examples/icons/bmp32x32.png
clientutils_examples/icons/brd32x32.png
clientutils_examples/icons/button-arrow-up-icon.png
clientutils_examples/icons/c32x32.png
clientutils_examples/icons/cdr32x32.png
clientutils_examples/icons/cpp32x32.png
clientutils_examples/icons/css32x32.png
clientutils_examples/icons/dat32x32.png
clientutils_examples/icons/divx32x32.png
clientutils_examples/icons/dmg32x32.png
clientutils_examples/icons/doc.png
clientutils_examples/icons/doc32x32.png
clientutils_examples/icons/docm32x32.png
clientutils_examples/icons/document32x32.png
clientutils_examples/icons/document_down.png
clientutils_examples/icons/document_edit.png
clientutils_examples/icons/document_error.png
clientutils_examples/icons/docx32x32.png
clientutils_examples/icons/dotx32x32.png
clientutils_examples/icons/dwg32x32.png
clientutils_examples/icons/dxf.png
clientutils_examples/icons/dxf32x32.png
clientutils_examples/icons/eap32x32.png
clientutils_examples/icons/eml32x32.png
clientutils_examples/icons/epf32x32.png
clientutils_examples/icons/eps32x32.png
clientutils_examples/icons/exe32x32.png
clientutils_examples/icons/file32x32.png
clientutils_examples/icons/flv32x32.png
clientutils_examples/icons/folder.png
clientutils_examples/icons/folder32x32.png
clientutils_examples/icons/folder_view.png
pyclientutils-0.0.5.dist-info/METADATA
pyclientutils-0.0.5.dist-info/WHEEL
pyclientutils-0.0.5.dist-info/entry_points.txt
pyclientutils-0.0.5.dist-info/licenses/LICENSE
pyclientutils-0.0.5.dist-info/RECORD
