Metadata-Version: 2.4
Name: pyclientutils
Version: 0.0.5
Summary: nicegui based Scholia
Project-URL: Home, https://github.com/WolfgangFahl/pyclientutils
Author-email: Wolfgang Fahl <wf@bitplan.com>
License-Expression: Apache-2.0
License-File: LICENSE
Classifier: Development Status :: 4 - Beta
Classifier: Environment :: Web Environment
Classifier: Intended Audience :: Developers
Classifier: Intended Audience :: Education
Classifier: Intended Audience :: Science/Research
Classifier: License :: OSI Approved :: Apache Software License
Classifier: Operating System :: OS Independent
Classifier: Programming Language :: Python :: 3 :: Only
Classifier: Programming Language :: Python :: 3.10
Classifier: Programming Language :: Python :: 3.11
Classifier: Programming Language :: Python :: 3.12
Classifier: Programming Language :: Python :: 3.13
Classifier: Topic :: Software Development :: User Interfaces
Requires-Python: >=3.10
Requires-Dist: copykitten>=2.0.0
Requires-Dist: fastapi>=0.128.0
Requires-Dist: httpx>=0.28.1
Requires-Dist: pillow>=12.1.0
Requires-Dist: pybasemkit>=0.1.6
Requires-Dist: requests>=2.31.0
Requires-Dist: uvicorn>=0.40.0
